nonebot_plugin_mai_online_lineup/__init__.py
nonebot_plugin_mai_online_lineup/data.json
nonebot_plugin_mai_online_lineup-1.0.2.dist-info/LICENSE
nonebot_plugin_mai_online_lineup-1.0.2.dist-info/METADATA
nonebot_plugin_mai_online_lineup-1.0.2.dist-info/WHEEL
nonebot_plugin_mai_online_lineup-1.0.2.dist-info/RECORD
