Metadata-Version: 2.1
Name: nonebot-plugin-mai-online-lineup
Version: 1.0.2
Summary: Nonebot 舞萌线上排卡插件
License: MIT
Author: shengwang52005
Author-email: shengwang52005@163.com
Requires-Python: >=3.11,<4.0
Classifier: License :: OSI Approved :: MIT License
Classifier: Programming Language :: Python :: 3
Classifier: Programming Language :: Python :: 3.11
Requires-Dist: nonebot2 (>=2.3.1,<3.0.0)
